minimega.py
minimega-2.9.dist-info/METADATA
minimega-2.9.dist-info/WHEEL
minimega-2.9.dist-info/top_level.txt
minimega-2.9.dist-info/RECORD
